bettersis/__init__.py
bettersis/__main__.py
bettersis/_version.py
bettersis/bettersis.py
bettersis/history_utils.py
bettersis/siscompleter.py
bettersis/texteditor.py
bettersis/update_checker.py
bettersis/web_utils.py
bettersis-1.2.1.dist-info/METADATA
bettersis-1.2.1.dist-info/RECORD
bettersis-1.2.1.dist-info/WHEEL
bettersis-1.2.1.dist-info/entry_points.txt
bettersis-1.2.1.dist-info/top_level.txt
