Metadata-Version: 2.1
Name: bettersis
Version: 1.2.1
Summary: The modern shell for SIS (the circuit simulator and optimizer)
Home-page: https://github.com/mario33881/betterSIS
Author: Zenaro Stefano (mario33881)
Author-email: mariortgasd@hotmail.com
License: MIT
Keywords: SIS BLIF
Platform: UNKNOWN
Classifier: Development Status :: 5 - Production/Stable
Classifier: License :: OSI Approved :: MIT License
Classifier: Programming Language :: Python :: 3
Classifier: Operating System :: Unix
Requires-Python: >=3
Requires-Dist: siswrapper (==1.2.2)
Requires-Dist: prompt-toolkit (==3.0.20)
Requires-Dist: certifi (==2021.5.30)
Requires-Dist: blifparser (==1.0.0)
